Slim3ZhongwenWendang/README.md
Slim3ZhongwenWendang/__init__.py
Slim3ZhongwenWendang/__main__.py
Slim3ZhongwenWendang/file.epub
Slim3ZhongwenWendang/index.html
Slim3ZhongwenWendang/css/__init__.py
Slim3ZhongwenWendang/css/annotations.css
Slim3ZhongwenWendang/css/main.css
Slim3ZhongwenWendang/css/normalize.css
Slim3ZhongwenWendang/css/popup.css
Slim3ZhongwenWendang/font/__init__.py
Slim3ZhongwenWendang/font/fontello.eot
Slim3ZhongwenWendang/font/fontello.svg
Slim3ZhongwenWendang/font/fontello.ttf
Slim3ZhongwenWendang/font/fontello.woff
Slim3ZhongwenWendang/img/__init__.py
Slim3ZhongwenWendang/img/annotator-glyph-sprite.png
Slim3ZhongwenWendang/img/annotator-icon-sprite.png
Slim3ZhongwenWendang/img/apple-touch-icon.png
Slim3ZhongwenWendang/img/cancelfullscreen.png
Slim3ZhongwenWendang/img/close.png
Slim3ZhongwenWendang/img/fullscreen.png
Slim3ZhongwenWendang/img/loader.gif
Slim3ZhongwenWendang/img/menu-icon.png
Slim3ZhongwenWendang/img/save.png
Slim3ZhongwenWendang/img/saved.png
Slim3ZhongwenWendang/img/settings-s.png
Slim3ZhongwenWendang/img/settings.png
Slim3ZhongwenWendang/img/star.png
Slim3ZhongwenWendang/js/__init__.py
Slim3ZhongwenWendang/js/epub.js
Slim3ZhongwenWendang/js/epub.min.js
Slim3ZhongwenWendang/js/epub.min.map
Slim3ZhongwenWendang/js/hooks.min.js
Slim3ZhongwenWendang/js/hooks.min.map
Slim3ZhongwenWendang/js/reader.js
Slim3ZhongwenWendang/js/reader.js.map
Slim3ZhongwenWendang/js/reader.min.js
Slim3ZhongwenWendang/js/reader.min.map
Slim3ZhongwenWendang/js/hooks/__init__.py
Slim3ZhongwenWendang/js/hooks/extensions/__init__.py
Slim3ZhongwenWendang/js/hooks/extensions/highlight.js
Slim3ZhongwenWendang/js/libs/__init__.py
Slim3ZhongwenWendang/js/libs/jquery.min.js
Slim3ZhongwenWendang/js/libs/localforage.min.js
Slim3ZhongwenWendang/js/libs/screenfull.js
Slim3ZhongwenWendang/js/libs/screenfull.min.js
Slim3ZhongwenWendang/js/libs/zip.min.js
Slim3ZhongwenWendang/js/plugins/__init__.py
Slim3ZhongwenWendang/js/plugins/hypothesis.js
slim3_zhongwen_wendang-2024.3.2.0.dist-info/METADATA
slim3_zhongwen_wendang-2024.3.2.0.dist-info/WHEEL
slim3_zhongwen_wendang-2024.3.2.0.dist-info/entry_points.txt
slim3_zhongwen_wendang-2024.3.2.0.dist-info/top_level.txt
slim3_zhongwen_wendang-2024.3.2.0.dist-info/RECORD
